On_school/simu2.v
module simu2 (
    input wire [2:0] in,
    output wire [1:0] out
);
    wire w1;
    assign w1 = (in[0] & in[1]);
    assign out[0] = (w1 | ~(in [2]));
    assign out[1] = ~in[2];

endmodule

On_school/tb_simu2.v
    //timescale dinh nghia don gi thoi gian trong luc mo phong
    `timescale 1ps/1ps
module tb ;

    reg [2:0] in;
    wire [1:0] out;
    
    simu2 uut(
        .in(in),
        .out(out)
    );


    initial begin   

        $dumpfile("simu2.vcd");  // Đặt tên file VCD
        $dumpvars(0, tb); // Ghi tất cả các tín hiệu trong testbench vào file VCD

        $display("================TEST_CASE==================");
        in = 3'b000; #10;
        $display("in = %b, out = %b", in, out);

        in = 3'b001; #10;
        $display("in = %b, out = %b", in, out);

        in = 3'b010; #10;
        $display("in = %b, out = %b", in, out);

        in = 3'b011; #10;
        $display("in = %b, out = %b", in, out);

        in = 3'b100; #10;
        $display("in = %b, out = %b", in, out);

        in = 3'b101; #10;
        $display("in = %b, out = %b", in, out);

        in = 3'b110; #10;
        $display("in = %b, out = %b", in, out);

        in = 3'b111; #10;
        $display("in = %b, out = %b", in, out);

        $display("================END_TEST====================");

        $finish; 


    end

endmodule

On_school/simu2.vcd
$date
	Fri Dec 12 10:45:02 2025
$end
$version
	Icarus Verilog
$end
$timescale
	1ps
$end
$scope module tb $end
$var wire 2 ! out [1:0] $end
$var reg 3 " in [2:0] $end
$scope module uut $end
$var wire 3 # in [2:0] $end
$var wire 1 $ w1 $end
$var wire 2 % out [1:0] $end
$upscope $end
$upscope $end
$enddefinitions $end
$comment Show the parameter values. $end
$dumpall
$end
#0
$dumpvars
b11 %
0$
b0 #
b0 "
b11 !
$end
#10
b1 "
b1 #
#20
b10 "
b10 #
#30
1$
b11 "
b11 #
#40
0$
b0 !
b0 %
b100 "
b100 #
#50
b101 "
b101 #
#60
b110 "
b110 #
#70
b1 !
b1 %
1$
b111 "
b111 #
