MUX_tutorial/8x1_mux/4x1_special_case/8x1_special_case.v
module  special_case (
    input wire [7:0] in,
    input wire [2:0] sel,
    output wire out
);
    wire low_case;
    wire high_case;
    //module instantiation
    //mux low case 0 -> 3
    mux_4x1 m1 (
        .in(in[3:0]),
        .sel(sel[1:0]),
        .out(low_case)
    );

    //mux high case 4 -> 7
    mux_4x1 m2 (
        .in(in[7:4]),
        .sel(sel[1:0]),
        .out(high_case)
    );

    //final 2 to 1 select
    assign out = sel[2] ? low_case : high_case;
    
endmodule 

module mux_4x1 (
    input wire [3:0] in,
    input wire [1:0] sel,
    output wire out
);
    assign out = in[sel];
    
endmodule

MUX_tutorial/8x1_mux/4x1_special_case/tb_special.v
 `timescale 1ns/1ps

module tb_mux_8x1;

    reg  [0:7] in;
    reg  [2:0] sel;
    wire out;
 
    // Instantiate the DUT
    special_case uut (
        .in(in),
        .sel(sel),
        .out(out)
    );

    initial begin
        $dumpfile("8x1_waveform.vcd");
        $dumpvars(9,tb_mux_8x1);
        $display("=== TEST MUX 8x1 ===");

        // Gán giá trị cho input
        in = 8'b10110011;  

        // Test tất cả giá trị select
        sel = 3'b000; #10;
        $display("sel=%b => out=%b ", sel, out);

        sel = 3'b001; #10;
        $display("sel=%b => out=%b ", sel, out);

        sel = 3'b010; #10;
        $display("sel=%b => out=%b ", sel, out);

        sel = 3'b011; #10;
        $display("sel=%b => out=%b ", sel, out);

        sel = 3'b100; #10;
        $display("sel=%b => out=%b ", sel, out);

        sel = 3'b101; #10;
        $display("sel=%b => out=%b ", sel, out);

        sel = 3'b110; #10;
        $display("sel=%b => out=%b ", sel, out);

        sel = 3'b111; #10;
        $display("sel=%b => out=%b ", sel, out);

        $display("=== END TEST ===");
        $finish;
    end

endmodule

MUX_tutorial/8x1_mux/4x1_special_case/8x1_waveform.vcd
$date
	Wed Dec 10 08:19:32 2025
$end
$version
	Icarus Verilog
$end
$timescale
	1ps
$end
$scope module tb_mux_8x1 $end
$var wire 1 ! out $end
$var reg 8 " in [0:7] $end
$var reg 3 # sel [2:0] $end
$scope module uut $end
$var wire 8 $ in [7:0] $end
$var wire 3 % sel [2:0] $end
$var wire 1 ! out $end
$var wire 1 & low_case $end
$var wire 1 ' high_case $end
$scope module m1 $end
$var wire 4 ( in [3:0] $end
$var wire 2 ) sel [1:0] $end
$var wire 1 & out $end
$upscope $end
$scope module m2 $end
$var wire 4 * in [3:0] $end
$var wire 2 + sel [1:0] $end
$var wire 1 ' out $end
$upscope $end
$upscope $end
$upscope $end
$enddefinitions $end
$comment Show the parameter values. $end
$dumpall
$end
#0
$dumpvars
b0 +
b1011 *
b0 )
b11 (
1'
1&
b0 %
b10110011 $
b0 #
b10110011 "
1!
$end
#10000
b1 )
b1 +
b1 #
b1 %
#20000
0!
0&
b10 )
0'
b10 +
b10 #
b10 %
#30000
1!
b11 )
1'
b11 +
b11 #
b11 %
#40000
1&
b0 )
b0 +
b100 #
b100 %
#50000
b1 )
b1 +
b101 #
b101 %
#60000
0!
0&
b10 )
0'
b10 +
b110 #
b110 %
#70000
b11 )
1'
b11 +
b111 #
b111 %
