MUX_tutorial/2X1/mux_2x1.v
module Mux_2x1 (a,b,sel,y);
    input wire a,b,sel;
    output reg y;

    always @(*) begin
        case (sel)
            1'b0: y = a;
            1'b1: y = b;
        endcase
    end

endmodule

MUX_tutorial/2X1/mux_2x1_testbench.v
`timescale 1ps/1ps

module testbench ;
    reg a_tb,b_tb,sel_tb;
    wire out;

    //module instant

    Mux_2x1 mux(
        .a(a_tb),
        .b(b_tb),
        .sel(sel_tb),
        .y(out)
    );

    initial begin
        $dumpfile("mux_2x1_test.vcd");
        $dumpvars(0, testbench);
        $monitor("Time = %d, a = %b, b = %b, select = %b, output =  %b",$time, a_tb, b_tb, sel_tb, out);
        //test case

        sel_tb = 0; a_tb = 0; b_tb = 0;
        #1;
        sel_tb = 0; a_tb = 0; b_tb = 1;
        #1;
        sel_tb = 0; a_tb = 1; b_tb = 0;
        #1
        sel_tb = 0; a_tb = 1; b_tb = 1;
        #1
        sel_tb = 1; a_tb = 0; b_tb = 0;
        #1
        sel_tb = 1; a_tb = 0; b_tb = 1;
        #1
        sel_tb = 1; a_tb = 1; b_tb = 0;
        #1
        sel_tb = 1; a_tb = 1; b_tb = 1;
        #1

        $finish;

    end
endmodule

MUX_tutorial/2X1/mux_2x1_test.vcd
$date
	Tue Dec  9 17:13:07 2025
$end
$version
	Icarus Verilog
$end
$timescale
	1ps
$end
$scope module testbench $end
$var wire 1 ! out $end
$var reg 1 " a_tb $end
$var reg 1 # b_tb $end
$var reg 1 $ sel_tb $end
$scope module mux $end
$var wire 1 " a $end
$var wire 1 # b $end
$var wire 1 $ sel $end
$var reg 1 ! y $end
$upscope $end
$upscope $end
$enddefinitions $end
$comment Show the parameter values. $end
$dumpall
$end
#0
$dumpvars
0$
0#
0"
0!
$end
#1
1#
#2
1!
0#
1"
#3
1#
#4
0!
0#
0"
1$
#5
1!
1#
#6
0!
0#
1"
#7
1!
1#
